Metadata-Version: 1.0
Name: random-var-distro
Version: 0.1
Summary: Probability distributions for continuous and discrete random variables
Home-page: UNKNOWN
Author: UNKNOWN
Author-email: UNKNOWN
License: UNKNOWN
Platform: UNKNOWN
